examples/__init__.py
examples/exports.py
examples/files.py
examples/folders.py
examples/policies.py
examples/scans.py
examples/users.py
examples/workbench.py
tenable_io/__init__.py
tenable_io/client.py
tenable_io/config.py
tenable_io/exceptions.py
tenable_io/log.py
tenable_io/util.py
tenable_io/api/__init__.py
tenable_io/api/access_groups.py
tenable_io/api/agent_config.py
tenable_io/api/agent_exclusions.py
tenable_io/api/agent_groups.py
tenable_io/api/agents.py
tenable_io/api/assets.py
tenable_io/api/base.py
tenable_io/api/bulk_operations.py
tenable_io/api/credentials.py
tenable_io/api/editor.py
tenable_io/api/exclusions.py
tenable_io/api/exports.py
tenable_io/api/file.py
tenable_io/api/filters.py
tenable_io/api/folders.py
tenable_io/api/groups.py
tenable_io/api/import_.py
tenable_io/api/models.py
tenable_io/api/networks.py
tenable_io/api/plugins.py
tenable_io/api/policies.py
tenable_io/api/sc_containers.py
tenable_io/api/sc_policy.py
tenable_io/api/sc_reports.py
tenable_io/api/sc_test_jobs.py
tenable_io/api/scanners.py
tenable_io/api/scans.py
tenable_io/api/server.py
tenable_io/api/session.py
tenable_io/api/tags.py
tenable_io/api/target_groups.py
tenable_io/api/users.py
tenable_io/api/workbenches.py
tenable_io/helpers/__init__.py
tenable_io/helpers/export.py
tenable_io/helpers/file.py
tenable_io/helpers/folder.py
tenable_io/helpers/permissions.py
tenable_io/helpers/policy.py
tenable_io/helpers/scan.py
tenable_io/helpers/workbench.py
tenable_io/parser/__init__.py
tenable_io/parser/workbenches.py
tenable_io-1.13.1.dist-info/LICENSE
tenable_io-1.13.1.dist-info/METADATA
tenable_io-1.13.1.dist-info/WHEEL
tenable_io-1.13.1.dist-info/top_level.txt
tenable_io-1.13.1.dist-info/RECORD
