Metadata-Version: 2.1
Name: tenable-io
Version: 1.13.1
Summary: Tenable.io API SDK
Home-page: https://github.com/tenable/Tenable.io-SDK-for-Python
Author: Tenable Network Security, Inc
Author-email: UNKNOWN
License: MIT License
Platform: UNKNOWN
Requires-Dist: requests (>=2.12.1)
Requires-Dist: six (>=1.10.0)
